{"textures":{"0":"modelengine:entity/carolla"},"elements":[{"from":[2.7863827,6.1759567,-9.853697],"to":[13.213617,8.176084,13.033697],"faces":{"east":{"uv":[9.4375,1.5,5.75,1.8125],"tintindex":0,"rotation":0,"texture":"#0"},"south":{"uv":[9.6875,7.25,8.0,7.5625],"tintindex":0,"rotation":0,"texture":"#0"},"north":{"uv":[9.8125,6.75,8.125,7.0625],"tintindex":0,"rotation":0,"texture":"#0"},"west":{"uv":[9.4375,1.875,5.75,2.1875],"tintindex":0,"rotation":0,"texture":"#0"},"up":{"uv":[1.6875,0.0,0.0,3.6875],"tintindex":0,"rotation":0,"texture":"#0"},"down":{"uv":[3.4375,3.6875,1.75,0.0],"tintindex":0,"rotation":0,"texture":"#0"}}}],"display":{"gui":{"rotation":[30,225,0]}}}